recc_co/__init__.py
recc_co-2.0.3.dist-info/LICENSE
recc_co-2.0.3.dist-info/METADATA
recc_co-2.0.3.dist-info/WHEEL
recc_co-2.0.3.dist-info/top_level.txt
recc_co-2.0.3.dist-info/RECORD
